gdmec23120233/__init__.py
gdmec23120233-0.1.1.dist-info/METADATA
gdmec23120233-0.1.1.dist-info/WHEEL
gdmec23120233-0.1.1.dist-info/entry_points.txt
gdmec23120233-0.1.1.dist-info/RECORD
